algo_utils_hr/__init__.py
algo_utils_hr/algo_typing.py
algo_utils_hr/data_analysis.py
algo_utils_hr/file_operations.py
algo_utils_hr/image_processing.py
algo_utils_hr/label_descriptions.txt
algo_utils_hr/matching_graphs.py
algo_utils_hr/measurements.py
algo_utils_hr/segmentation_features.py
algo_utils_hr/segmentation_processing.py
algo_utils_hr-1.1.2.dist-info/LICENSE
algo_utils_hr-1.1.2.dist-info/METADATA
algo_utils_hr-1.1.2.dist-info/WHEEL
algo_utils_hr-1.1.2.dist-info/top_level.txt
algo_utils_hr-1.1.2.dist-info/RECORD
