Metadata-Version: 2.1
Name: algo_utils_hr
Version: 1.1.2
Summary: A collection of utility functions for algorithm development and data analysis
Home-page: https://github.com/High-Rad/algo_utils.git
Author: Shalom Rochman
Author-email: shalom.rochman@high-rad.com
Classifier: Programming Language :: Python :: 3
Classifier: License :: OSI Approved :: MIT License
Classifier: Operating System :: OS Independent
Requires-Python: >=3.10
License-File: LICENSE
Requires-Dist: jsonschema~=4.21.1
Requires-Dist: nibabel~=5.2.1
Requires-Dist: numpy~=1.26.3
Requires-Dist: pandas~=2.2.2
Requires-Dist: networkx~=3.1
Requires-Dist: scikit-image~=0.24.0
Requires-Dist: scipy~=1.14.0
Requires-Dist: tqdm~=4.65.0
Requires-Dist: xlsxwriter~=3.1.9
Requires-Dist: medpy~=0.5.2
Requires-Dist: matplotlib~=3.9.2
